dtg/__init__.py
dtg/add/__init__.py
dtg/add/excess.py
dtg/add/transform.py
dtg/dependence/__init__.py
dtg/dependence/acf.py
dtg/dependence/runde.py
dtg/self_similarity/__init__.py
dtg/self_similarity/higuchi.py
dtg/self_similarity/rs.py
dtg/stationary/__init__.py
dtg/stationary/dierckx.py
dtg/stationary/giratis.py
dtg/tail/__init__.py
dtg/tail/ks.py
dtg/tail/mse.py
dtg/tail/prep.py
dtg/tail/qq_powerlaw.py
dtg/tail/sequential.py
dtg/tail/estimate/__init__.py
dtg/tail/estimate/estimator.py
dtg/tail/estimate/group.py
dtg/tail/estimate/hill.py
dtg/tail/estimate/jackknife.py
dtg/tail/estimate/moment.py
dtg/tail/estimate/pickands.py
dtg/tail/estimate/ratio.py
dtg/tail/estimate/ro.py
dtg/tail/estimate/uh.py
dtg/tail/estimate/vries.py
dtg-1.0.3.1.dist-info/LICENSE
dtg-1.0.3.1.dist-info/METADATA
dtg-1.0.3.1.dist-info/WHEEL
dtg-1.0.3.1.dist-info/top_level.txt
dtg-1.0.3.1.dist-info/RECORD
