Metadata-Version: 2.1
Name: dtg
Version: 1.0.3.1
Summary: Heavy-tailed distribution analysis
Home-page: https://gitlab.com/BoBeni/DTG
Author: Maksim Ryzhov
Author-email: ryzhov@phystech.edu
License: MIT
Platform: UNKNOWN
License-File: LICENSE
Requires-Dist: numpy
Requires-Dist: scipy
Requires-Dist: statsmodels
